rankit/Merge.py
rankit/__init__.py
rankit/Ranker/LeastViolatedRank.py
rankit/Ranker/TimeSeriesRanker.py
rankit/Ranker/UnsupervisedRanker.py
rankit/Ranker/__init__.py
rankit/Ranker/tests/__init__.py
rankit/Ranker/tests/test_ranker.py
rankit/Ranker/tests/test_timeseries_ranker.py
rankit/Table/Table.py
rankit/Table/__init__.py
rankit/Table/test/__init__.py
rankit/Table/test/test_table.py
rankit-0.3.3.dist-info/LICENSE
rankit-0.3.3.dist-info/METADATA
rankit-0.3.3.dist-info/WHEEL
rankit-0.3.3.dist-info/top_level.txt
rankit-0.3.3.dist-info/RECORD
