Metadata-Version: 2.1
Name: rankit
Version: 0.3.3
Summary: A simple ranking solution for matches.
Home-page: http://github.com/wattlebird/ranking
Author: Ronnie Wang
Author-email: geniusxiaoguai@gmail.com
License: MIT
Classifier: Intended Audience :: Science/Research
Classifier: Intended Audience :: Developers
Classifier: License :: OSI Approved
Classifier: Programming Language :: Python
Classifier: Topic :: Scientific/Engineering
Classifier: Operating System :: Unix
Classifier: Programming Language :: Python :: 2.7
Classifier: Programming Language :: Python :: 3.5
Classifier: Programming Language :: Python :: 3.6
License-File: LICENSE
Requires-Dist: numpy
Requires-Dist: scipy
Requires-Dist: pandas
